pyproject_patcher/__init__.py
pyproject_patcher/logging.py
pyproject_patcher/patcher.py
pyproject_patcher/requirements.py
pyproject_patcher/settings.py
pyproject_patcher/types.py
pyproject_patcher/version.py
pyproject_patcher/stubs/distlib/util.pyi
pyproject_patcher/stubs/setuptools_git_versioning/__init__.pyi
pyproject_patcher/stubs/setuptools_git_versioning/defaults.pyi
pyproject_patcher/tools/__init__.py
pyproject_patcher/tools/setuptools_git_versioning.py
pyproject_patcher-0.3.0.dist-info/METADATA
pyproject_patcher-0.3.0.dist-info/WHEEL
pyproject_patcher-0.3.0.dist-info/licenses/LICENSE
pyproject_patcher-0.3.0.dist-info/RECORD
