Metadata-Version: 2.4
Name: pyproject_patcher
Version: 0.3.0
Summary: Collection of convenience functions to patch `pyproject.toml` in place
Project-URL: documentation, https://pyproject-patcher.readthedocs.io/en/stable/
Project-URL: source, https://github.com/claui/pyproject-patcher
Author-email: Claudia Pellegrino <clau@tiqua.de>
License-Expression: Apache-2.0
License-File: LICENSE
Classifier: Development Status :: 3 - Alpha
Classifier: Operating System :: POSIX :: Linux
Classifier: Topic :: Software Development :: Build Tools
Requires-Python: >=3.12
Requires-Dist: distlib
Requires-Dist: in-place
Requires-Dist: pyxdg
Requires-Dist: tomlkit
Requires-Dist: typing-extensions
